kemopro
