Metadata-Version: 1.0
Name: kemopro
Version: 4.0
Summary: a pip-installable package example
Home-page: https://github.com/bgse/hellostackoverflow
Author: Benjamin Gerfelder
Author-email: benjamin.gerfelder@gmail.com
License: MIT
Keywords: example
Platform: UNKNOWN
